napari_stable_diffusion/__init__.py
napari_stable_diffusion/_widget.py
napari_stable_diffusion/_widget_img2img.py
napari_stable_diffusion/_widget_inpaint.py
napari_stable_diffusion/napari.yaml
napari_stable_diffusion/utils.py
napari_stable_diffusion/_tests/__init__.py
napari_stable_diffusion/_tests/test_widget.py
napari_stable_diffusion-0.1.1.dist-info/LICENSE
napari_stable_diffusion-0.1.1.dist-info/METADATA
napari_stable_diffusion-0.1.1.dist-info/WHEEL
napari_stable_diffusion-0.1.1.dist-info/entry_points.txt
napari_stable_diffusion-0.1.1.dist-info/top_level.txt
napari_stable_diffusion-0.1.1.dist-info/RECORD
