Metadata-Version: 2.1
Name: napari-stable-diffusion
Version: 0.1.1
Summary: A demo of stable diffusion in napari
Home-page: https://github.com/kephale/napari-stable-diffusion
Author: Kyle Harrington
Author-email: napari@kyleharrington.com
License: BSD-3-Clause
Project-URL: Bug Tracker, https://github.com/kephale/napari-stable-diffusion/issues
Project-URL: Documentation, https://github.com/kephale/napari-stable-diffusion#README.md
Project-URL: Source Code, https://github.com/kephale/napari-stable-diffusion
Project-URL: User Support, https://github.com/kephale/napari-stable-diffusion/issues
Classifier: Development Status :: 2 - Pre-Alpha
Classifier: Framework :: napari
Classifier: Intended Audience :: Developers
Classifier: License :: OSI Approved :: BSD License
Classifier: Operating System :: OS Independent
Classifier: Programming Language :: Python
Classifier: Programming Language :: Python :: 3
Classifier: Programming Language :: Python :: 3 :: Only
Classifier: Programming Language :: Python :: 3.8
Classifier: Programming Language :: Python :: 3.9
Classifier: Programming Language :: Python :: 3.10
Classifier: Topic :: Scientific/Engineering :: Image Processing
Requires-Python: >=3.8
License-File: LICENSE
Requires-Dist: napari
Requires-Dist: napari-plugin-engine (>=0.1.4)
Requires-Dist: numpy
Requires-Dist: magicgui
Requires-Dist: qtpy
Requires-Dist: diffusers
Requires-Dist: transformers
Requires-Dist: torch
Provides-Extra: testing
Requires-Dist: tox ; extra == 'testing'
Requires-Dist: pytest ; extra == 'testing'
Requires-Dist: pytest-cov ; extra == 'testing'
Requires-Dist: pytest-qt ; extra == 'testing'
Requires-Dist: napari ; extra == 'testing'
Requires-Dist: pyqt5 ; extra == 'testing'
